LICENSE
README.md
setup.py
ebench/__init__.py
ebench/__main__.py
ebench.egg-info/PKG-INFO
ebench.egg-info/SOURCES.txt
ebench.egg-info/dependency_links.txt
ebench.egg-info/top_level.txt
ebench/core/__init__.py
ebench/core/dataset.py
ebench/core/logger.py
ebench/core/media.py
ebench/core/metric.py
ebench/core/model.py
ebench/core/utils.py