Metadata-Version: 2.1
Name: ebench
Version: 1.0.0
Summary: Ebench is an ehancement benchmark tool.
Home-page: https://github.com/OpenMeow/ebench
Author: Kai Jin
Author-email: atranitell@gmail.com
License: Apache 2.0 Licence
Platform: UNKNOWN
Classifier: Programming Language :: Python :: 3.8
Classifier: Programming Language :: Python :: 3.9
Classifier: Programming Language :: Python :: 3.10
Classifier: License :: OSI Approved :: Apache Software License
Classifier: Operating System :: OS Independent
Classifier: Intended Audience :: Science/Research
Classifier: Topic :: Scientific/Engineering :: Artificial Intelligence
License-File: LICENSE
